README.txt
setup.cfg
setup.py
docs/HISTORY.txt
pcommerce/__init__.py
pcommerce.payment.invoice.egg-info/PKG-INFO
pcommerce.payment.invoice.egg-info/SOURCES.txt
pcommerce.payment.invoice.egg-info/dependency_links.txt
pcommerce.payment.invoice.egg-info/entry_points.txt
pcommerce.payment.invoice.egg-info/namespace_packages.txt
pcommerce.payment.invoice.egg-info/not-zip-safe
pcommerce.payment.invoice.egg-info/requires.txt
pcommerce.payment.invoice.egg-info/top_level.txt
pcommerce/payment/__init__.py
pcommerce/payment/invoice/__init__.py
pcommerce/payment/invoice/configure.zcml
pcommerce/payment/invoice/data.py
pcommerce/payment/invoice/interfaces.py
pcommerce/payment/invoice/plugin.py
pcommerce/payment/invoice/browser/__init__.py
pcommerce/payment/invoice/browser/base.py
pcommerce/payment/invoice/browser/configure.zcml
pcommerce/payment/invoice/browser/confirmation.pt
pcommerce/payment/invoice/browser/confirmation.py
pcommerce/payment/invoice/browser/icon.gif
pcommerce/payment/invoice/browser/logo.gif
pcommerce/payment/invoice/browser/overview.pt
pcommerce/payment/invoice/browser/overview.py
pcommerce/payment/invoice/browser/payment.pt
pcommerce/payment/invoice/browser/payment.py
pcommerce/payment/invoice/browser/process.py
pcommerce/payment/invoice/i18n/pcommerce-de.mo
pcommerce/payment/invoice/i18n/pcommerce-de.po
pcommerce/payment/invoice/i18n/pcommerce-nl.po
pcommerce/payment/invoice/i18n/pcommerce.pot
pcommerce/payment/invoice/profiles/default/metadata.xml
pcommerce/payment/invoice/profiles/default/propertiestool.xml