Metadata-Version: 1.0
Name: pcommerce.payment.invoice
Version: 1.0b3
Summary: A invoice payment method for PCommerce
Home-page: http://raptus.com
Author: Raptus AG
Author-email: skaeser@raptus.com
License: GPL
Platform: UNKNOWN
Classifier: Programming Language :: Python
Classifier: Topic :: Software Development :: Libraries :: Python Modules
